gnnenrich/__init__.py
gnnenrich/py.typed
gnnenrich/random_lists.py
gnnenrich/scoring.py
gnnenrich-1.1.0.dist-info/LICENSE
gnnenrich-1.1.0.dist-info/METADATA
gnnenrich-1.1.0.dist-info/WHEEL
gnnenrich-1.1.0.dist-info/top_level.txt
gnnenrich-1.1.0.dist-info/RECORD
