Metadata-Version: 2.2
Name: gnnenrich
Version: 1.1.0
Summary: Enrichment Analysis based on GNN
Author-email: Mallek MZIOU <mallek.mziou@cea.fr>, Pierrick ROGER <pierrick.roger@cea.fr>
License: 
Project-URL: Homepage, https://gitlab.com/cnrgh/gnn-enrich/gnn-enrich
Project-URL: Repository, https://gitlab.com/cnrgh/gnn-enrich/gnn-enrich
Project-URL: Bug Tracker, https://gitlab.com/cnrgh/gnn-enrich/gnn-enrich/issues
Keywords: GNN,enrichment
Classifier: Programming Language :: Python :: 3
Classifier: License :: CeCILL-C Free Software License Agreement (CECILL-C)
Classifier: Operating System :: OS Independent
Requires-Python: >=3.11
License-File: LICENSE
Requires-Dist: numpy
Requires-Dist: scipy
Requires-Dist: tqdm
Provides-Extra: dev
Requires-Dist: build; extra == "dev"
Requires-Dist: twine; extra == "dev"
Requires-Dist: pytest; extra == "dev"
Requires-Dist: pylint; extra == "dev"
Requires-Dist: mypy; extra == "dev"
Requires-Dist: coverage; extra == "dev"
Provides-Extra: doc
Requires-Dist: sphinx; extra == "doc"
Requires-Dist: sphinx_rtd_theme; extra == "doc"
